MANIFEST.in
README.md
setup.cfg
setup.py
eyewitness/__init__.py
eyewitness/audience_id.py
eyewitness/config.py
eyewitness/dataset_util.py
eyewitness/detection_result_filter.py
eyewitness/detection_utils.py
eyewitness/evaluation.py
eyewitness/feedback_msg_utils.py
eyewitness/flask_server.py
eyewitness/image_id.py
eyewitness/image_utils.py
eyewitness/object_classifier.py
eyewitness/object_detector.py
eyewitness/utils.py
eyewitness.egg-info/PKG-INFO
eyewitness.egg-info/SOURCES.txt
eyewitness.egg-info/dependency_links.txt
eyewitness.egg-info/requires.txt
eyewitness.egg-info/top_level.txt
eyewitness/font/FiraMono-Medium.otf
eyewitness/models/__init__.py
eyewitness/models/db_proxy.py
eyewitness/models/detection_models.py
eyewitness/models/feedback_models.py
eyewitness/mot/__init__.py
eyewitness/mot/evaluation.py
eyewitness/mot/tracker.py
eyewitness/mot/video.py
eyewitness/mot/visualize_mot.py
eyewitness/result_handler/__init__.py
eyewitness/result_handler/db_writer.py